{
   "html_attributions" : [],
   "result" : {
      "address_components" : [
         {
            "long_name" : "808",
            "short_name" : "808",
            "types" : [ "street_number" ]
         },
         {
            "long_name" : "West End Avenue",
            "short_name" : "West End Ave",
            "types" : [ "route" ]
         },
         {
            "long_name" : "Manhattan",
            "short_name" : "Manhattan",
            "types" : [ "sublocality_level_1", "sublocality", "political" ]
         },
         {
            "long_name" : "New York",
            "short_name" : "New York",
            "types" : [ "locality", "political" ]
         },
         {
            "long_name" : "New York County",
            "short_name" : "New York County",
            "types" : [ "administrative_area_level_2", "political" ]
         },
         {
            "long_name" : "New York",
            "short_name" : "NY",
            "types" : [ "administrative_area_level_1", "political" ]
         },
         {
            "long_name" : "United States",
            "short_name" : "US",
            "types" : [ "country", "political" ]
         },
         {
            "long_name" : "10025",
            "short_name" : "10025",
            "types" : [ "postal_code" ]
         }
      ],
      "adr_address" : "\u003cspan class=\"street-address\"\u003e808 West End Ave\u003c/span\u003e, \u003cspan class=\"locality\"\u003eNew York\u003c/span\u003e, \u003cspan class=\"region\"\u003eNY\u003c/span\u003e \u003cspan class=\"postal-code\"\u003e10025\u003c/span\u003e, \u003cspan class=\"country-name\"\u003eUSA\u003c/span\u003e",
      "formatted_address" : "808 West End Ave, New York, NY 10025, USA",
      "geometry" : {
         "location" : {
            "lat" : 40.79724059999999,
            "lng" : -73.9713259
         },
         "viewport" : {
            "northeast" : {
               "lat" : 40.79848363029149,
               "lng" : -73.97001191970848
            },
            "southwest" : {
               "lat" : 40.79578566970849,
               "lng" : -73.9727098802915
            }
         }
      },
      "icon" : "https://maps.gstatic.com/mapfiles/place_api/icons/geocode-71.png",
      "id" : "85fc523d367d3c4cb29db83036957cf71ebf63be",
      "name" : "808 West End Ave",
      "place_id" : "ChIJ4wF7HSb2wokRNdHrLg0_A2g",
      "reference" : "ChIJ4wF7HSb2wokRNdHrLg0_A2g",
      "scope" : "GOOGLE",
      "types" : [ "premise" ],
      "url" : "https://maps.google.com/?q=808+West+End+Ave,+New+York,+NY+10025,+USA&ftid=0x89c2f6261d7b01e3:0x68033f0d2eebd135",
      "utc_offset" : -240,
      "vicinity" : "Manhattan"
   },
   "status" : "OK"
}

